{
  "ANL": {
    "detail": "Bitwise AND",
    "description": "Performs a bitwise AND operation between operands.\r\n\r\nDoes not affect value of second operand.",
    "valid_operands": [
      [
        {
          "operand": "accumulator",
          "when_first_is": "any"
        },
        {
          "operand": "carryFlag",
          "when_first_is": "any"
        },
        {
          "operand": "internalRamAddress",
          "when_first_is": "any"
        }
      ],
      [
        {
          "operand": "accumulator",
          "when_first_is": "internalRamAddress"
        },
        {
          "operand": "addressInR0OrR1",
          "when_first_is": "accumulator"
        },
        {
          "operand": "bitAddress",
          "when_first_is": "carryFlag"
        },
        {
          "operand": "data",
          "when_first_is": "internalRamAddress"
        },
        {
          "operand": "data",
          "when_first_is": "accumulator"
        },
        {
          "operand": "negatedBitAddress",
          "when_first_is": "carryFlag"
        },
        {
          "operand": "helperRegisters",
          "when_first_is": "accumulator"
        }
      ]
    ],
    "affected_flags": [],
    "dont_generate_syntax": false,
    "dont_duplicate_in_all_docs": false,
    "prefix": "",
    "prefix_required": false,
    "label": null,
    "addressingModes": []
  },
  "ORL": {
    "detail": "Bitwise OR",
    "description": "Performs a bitwise OR operation between operands.\r\n\r\nDoes not affect value of second operand.",
    "valid_operands": [
      [
        {
          "operand": "accumulator",
          "when_first_is": "any"
        },
        {
          "operand": "carryFlag",
          "when_first_is": "any"
        },
        {
          "operand": "internalRamAddress",
          "when_first_is": "any"
        }
      ],
      [
        {
          "operand": "accumulator",
          "when_first_is": "internalRamAddress"
        },
        {
          "operand": "addressInR0OrR1",
          "when_first_is": "accumulator"
        },
        {
          "operand": "bitAddress",
          "when_first_is": "carryFlag"
        },
        {
          "operand": "data",
          "when_first_is": "internalRamAddress"
        },
        {
          "operand": "data",
          "when_first_is": "accumulator"
        },
        {
          "operand": "negatedBitAddress",
          "when_first_is": "carryFlag"
        },
        {
          "operand": "helperRegisters",
          "when_first_is": "accumulator"
        }
      ]
    ],
    "affected_flags": [],
    "dont_generate_syntax": false,
    "dont_duplicate_in_all_docs": false,
    "prefix": "",
    "prefix_required": false,
    "label": null,
    "addressingModes": []
  },
  "XRL": {
    "detail": "Bitwise XOR",
    "description": "Performs a bitwise XOR operation between operands.\r\n\r\nDoes not affect value of second operand.",
    "valid_operands": [
      [
        {
          "operand": "accumulator",
          "when_first_is": "any"
        },
        {
          "operand": "carryFlag",
          "when_first_is": "any"
        },
        {
          "operand": "internalRamAddress",
          "when_first_is": "any"
        }
      ],
      [
        {
          "operand": "accumulator",
          "when_first_is": "internalRamAddress"
        },
        {
          "operand": "addressInR0OrR1",
          "when_first_is": "accumulator"
        },
        {
          "operand": "bitAddress",
          "when_first_is": "carryFlag"
        },
        {
          "operand": "data",
          "when_first_is": "internalRamAddress"
        },
        {
          "operand": "data",
          "when_first_is": "accumulator"
        },
        {
          "operand": "negatedBitAddress",
          "when_first_is": "carryFlag"
        },
        {
          "operand": "helperRegisters",
          "when_first_is": "accumulator"
        }
      ]
    ],
    "affected_flags": [],
    "dont_generate_syntax": false,
    "dont_duplicate_in_all_docs": false,
    "prefix": "",
    "prefix_required": false,
    "label": null,
    "addressingModes": []
  },
  "CLR": {
    "detail": "Clear",
    "description": "Clear (set to 0) value of the Accumulator, the Carry flag or a bit in RAM",
    "valid_operands": [
      [
        {
          "operand": "accumulator",
          "when_first_is": "any"
        },
        {
          "operand": "bitAddress",
          "when_first_is": "any"
        },
        {
          "operand": "carryFlag",
          "when_first_is": "any"
        }
      ]
    ],
    "affected_flags": [],
    "dont_generate_syntax": false,
    "dont_duplicate_in_all_docs": false,
    "prefix": "",
    "prefix_required": false,
    "label": null,
    "addressingModes": []
  },
  "CPL": {
    "detail": "Complement",
    "description": "Complements (reverses) value of the Accumulator, the Carry flag or a bit in RAM.\r\n\r\nThe Carry flag or bit in RAM is:\r\n - unset (0) if it was set (1)\r\n - set (1) if it was unset (0)\r\n\r\nEach bit in the Accumulator is subjected to the same operation as Carry flag or bit in RAM.\r\n\r\n\u003E If value of Accumulator was 10101001 then it will be set to 01010110",
    "valid_operands": [
      [
        {
          "operand": "accumulator",
          "when_first_is": "any"
        },
        {
          "operand": "bitAddress",
          "when_first_is": "any"
        },
        {
          "operand": "carryFlag",
          "when_first_is": "any"
        }
      ]
    ],
    "affected_flags": [],
    "dont_generate_syntax": false,
    "dont_duplicate_in_all_docs": false,
    "prefix": "",
    "prefix_required": false,
    "label": null,
    "addressingModes": []
  },
  "RL": {
    "detail": "Rotate left",
    "description": "Shifts bits of value stored in the Accumulator to the left.\r\n\r\nThe most significant bit is moved to the least significant bit.",
    "valid_operands": [
      [
        {
          "operand": "accumulator",
          "when_first_is": "any"
        }
      ]
    ],
    "affected_flags": [],
    "dont_generate_syntax": false,
    "dont_duplicate_in_all_docs": false,
    "prefix": "",
    "prefix_required": false,
    "label": null,
    "addressingModes": []
  },
  "RLC": {
    "detail": "Rotate left trough Carry flag",
    "description": "Shifts bits of value stored in the Accumulator to the left trough the Carry flag.\r\n\r\nValue of the Carry flag is moved to the least significant bit of the Accumulator.\r\n\r\nThe most significant bit is moved to the Carry flag.\r\n\r\nCan be used to multiply number by 2",
    "valid_operands": [
      [
        {
          "operand": "accumulator",
          "when_first_is": "any"
        }
      ]
    ],
    "affected_flags": [
      {
        "flag": "carry",
        "when_set": "",
        "when_unset": ""
      }
    ],
    "dont_generate_syntax": false,
    "dont_duplicate_in_all_docs": false,
    "prefix": "",
    "prefix_required": false,
    "label": null,
    "addressingModes": []
  },
  "RR": {
    "detail": "Rotate right",
    "description": "Shifts bits of value stored in the Accumulator to the right.\r\n\r\nThe least significant bit is moved to the most significant bit.",
    "valid_operands": [
      [
        {
          "operand": "accumulator",
          "when_first_is": "any"
        }
      ]
    ],
    "affected_flags": [],
    "dont_generate_syntax": false,
    "dont_duplicate_in_all_docs": false,
    "prefix": "",
    "prefix_required": false,
    "label": null,
    "addressingModes": []
  },
  "RRC": {
    "detail": "Rotate right trough Carry flag",
    "description": "Shifts bits of value stored in the Accumulator to the right trough the Carry flag.\r\n\r\nValue of the Carry flag is moved to the most significant bit of the Accumulator.\r\n\r\nThe least significant bit is moved to the Carry flag.\r\n\r\nCan be used to divide number by 2",
    "valid_operands": [
      [
        {
          "operand": "accumulator",
          "when_first_is": "any"
        }
      ]
    ],
    "affected_flags": [
      {
        "flag": "carry",
        "when_set": "",
        "when_unset": ""
      }
    ],
    "dont_generate_syntax": false,
    "dont_duplicate_in_all_docs": false,
    "prefix": "",
    "prefix_required": false,
    "label": null,
    "addressingModes": []
  },
  "SWAP": {
    "detail": "Swap nibbles of the Accumulator",
    "description": "Swap the most significant nibble of the Accumulator with the least significant nibble.\r\n\r\nEnd result will be the same as rotating Accumulator value 4 times.",
    "valid_operands": [
      [
        {
          "operand": "accumulator",
          "when_first_is": "any"
        }
      ]
    ],
    "affected_flags": [],
    "dont_generate_syntax": false,
    "dont_duplicate_in_all_docs": false,
    "prefix": "",
    "prefix_required": false,
    "label": null,
    "addressingModes": []
  },
  "SETB": {
    "detail": "Set Bit",
    "description": "Set (to 1) value of the Carry flag or a bit in RAM",
    "valid_operands": [
      [
        {
          "operand": "bitAddress",
          "when_first_is": "any"
        },
        {
          "operand": "carryFlag",
          "when_first_is": "any"
        }
      ]
    ],
    "affected_flags": [],
    "dont_generate_syntax": false,
    "dont_duplicate_in_all_docs": false,
    "prefix": "",
    "prefix_required": false,
    "label": null,
    "addressingModes": []
  }
}